{"type":"FeatureCollection","metadata":{"name":"Импорт из «пп_2.xlsx»","creator":"Yandex Map Constructor"},"features":[{"type":"Feature","id":0,"geometry":{"type":"Point","coordinates":[37.5835755,55.7471175]},"properties":{"description":"-","iconCaption":"-","iconContent":"1","marker-color":"#1e98ff"}},{"type":"Feature","id":1,"geometry":{"type":"Point","coordinates":[37.583909500000004,55.747049000000004]},"properties":{"description":"-","iconCaption":"-","iconContent":"2","marker-color":"#1e98ff"}}]}